[{"id":"rel-date-000091","source":"document_names:document-tridactyl-camscanner-07-11-2024-14-19-en","target":"dates_times:2024","source_name":"Document Tridactyl Camscanner 07 11 2024 14 19 En","target_name":"2024","type":"dated_on","weight":80,"evidence_segment_ids":["seg-document-tridactyl-camscanner-07-11-2024-14-19-en-title"],"evidence":[{"segment_id":"seg-document-tridactyl-camscanner-07-11-2024-14-19-en-title","transcript":"Document Tridactyl Camscanner 07 11 2024 14 19 En","timestamp":"00:00:00","excerpt":"Source document date: 2024 from Document Tridactyl Camscanner 07 11 2024 14 19 En","reason":"Document names assigned year date from source_title","relationship_type":"dated_on"}],"confidence":1.0}]